train.py
pulmoscan/__init__.py
pulmoscan/configurables.py
pulmoscan/constants.py
pulmoscan/metrics.py
pulmoscan/test_metrics.py
pulmoscan/datasets/__init__.py
pulmoscan/datasets/base.py
pulmoscan/datasets/rsna.py
pulmoscan/datasets/tagset.py
pulmoscan/datasets/test_rsna.py
pulmoscan/datasets/test_tagset.py
pulmoscan/models/__init__.py
pulmoscan/models/augmentation.py
pulmoscan/models/backbones.py
pulmoscan/models/base.py
pulmoscan/models/test_augmentation.py
pulmoscan/models/test_backbones.py
pulmoscan/parse/__init__.py
pulmoscan/parse/image.py
pulmoscan-0.1.4.dev12.data/data/pulmoscan_resources/resources/gin/alexnet_rsna_default.cfg
pulmoscan-0.1.4.dev12.data/data/pulmoscan_resources/resources/gin/densenet_rsna_default.cfg
pulmoscan-0.1.4.dev12.data/data/pulmoscan_resources/resources/gin/efficientnet_rsna_default.cfg
pulmoscan-0.1.4.dev12.data/data/pulmoscan_resources/resources/gin/mobilenet_rsna_default.cfg
pulmoscan-0.1.4.dev12.data/data/pulmoscan_resources/resources/gin/resnet50_rsna_default.cfg
pulmoscan-0.1.4.dev12.data/data/pulmoscan_resources/resources/gin/base/augmentation.cfg
pulmoscan-0.1.4.dev12.data/data/pulmoscan_resources/resources/gin/base/metrics.cfg
pulmoscan-0.1.4.dev12.data/data/pulmoscan_resources/resources/gin/base/model.cfg
pulmoscan-0.1.4.dev12.data/data/pulmoscan_resources/resources/gin/base/rsna.cfg
pulmoscan-0.1.4.dev12.data/data/pulmoscan_resources/resources/gin/base/train.cfg
pulmoscan-0.1.4.dev12.data/data/pulmoscan_resources/resources/mappings/rsna.txt
pulmoscan-0.1.4.dev12.data/data/pulmoscan_resources/resources/test/rsna/rsna_patient_to_label_test.csv
pulmoscan-0.1.4.dev12.data/data/pulmoscan_resources/resources/test/rsna/dicoms/0004cfab-14fd-4e49-80ba-63a80b6bddd6.dcm
pulmoscan-0.1.4.dev12.data/data/pulmoscan_resources/resources/test/rsna/dicoms/00313ee0-9eaa-42f4-b0ab-c148ed3241cd.dcm
pulmoscan-0.1.4.dev12.data/data/pulmoscan_resources/resources/test/rsna/dicoms/00322d4d-1c29-4943-afc9-b6754be640eb.dcm
pulmoscan-0.1.4.dev12.dist-info/METADATA
pulmoscan-0.1.4.dev12.dist-info/WHEEL
pulmoscan-0.1.4.dev12.dist-info/entry_points.txt
pulmoscan-0.1.4.dev12.dist-info/top_level.txt
pulmoscan-0.1.4.dev12.dist-info/RECORD
